MANIFEST.in
setup.py
gexecjs/README.md
gexecjs/__init__.py
gexecjs/runjs.py
gexecjs.egg-info/PKG-INFO
gexecjs.egg-info/SOURCES.txt
gexecjs.egg-info/dependency_links.txt
gexecjs.egg-info/top_level.txt