Metadata-Version: 2.4
Name: gexecjs
Version: 0.0.5
Summary: 调用 node 执行 js，可指定编码，支持异步返回
Home-page: https://github.com/Leviathangk/runjs
Author: 郭一会儿
Author-email: 1015295213@qq.com
License: MIT Licence
Keywords: js,runjs,execjs,grunjs,grun_js,pyexecjs
Platform: any
Dynamic: author
Dynamic: author-email
Dynamic: description
Dynamic: description-content-type
Dynamic: home-page
Dynamic: keywords
Dynamic: license
Dynamic: platform
Dynamic: summary
